hot_spot_analysis/__init__.py
hot_spot_analysis/hot_spot_analysis.py
hot_spot_analysis/utils/__init__.py
hot_spot_analysis/utils/combos.py
hot_spot_analysis/utils/demo.py
hot_spot_analysis/utils/general.py
hot_spot_analysis/utils/grouped_df.py
hot_spot_analysis/utils/lists.py
hot_spot_analysis-1.0.4.1.dist-info/LICENSE
hot_spot_analysis-1.0.4.1.dist-info/METADATA
hot_spot_analysis-1.0.4.1.dist-info/WHEEL
hot_spot_analysis-1.0.4.1.dist-info/top_level.txt
hot_spot_analysis-1.0.4.1.dist-info/RECORD
