Metadata-Version: 2.1
Name: hot-spot-analysis
Version: 1.0.4.1
Summary: Write a python function to calculate your metric(s), and run it over all clusters in your data. Find the cuts of the data driving your metrics.
Author-email: Philip Gundy <PhilipGundy@gmail.com>
License: MIT
Project-URL: Homepage, https://github.com/pgundy/hot_spot_analysis
Project-URL: Source, https://github.com/pgundy/hot_spot_analysis
Project-URL: Tracker, https://github.com/pgundy/hot_spot_analysis/issues
Requires-Python: >=3.9
License-File: LICENSE
Requires-Dist: pandas >=1.3.5
Requires-Dist: numpy >=1.21
Provides-Extra: dev
Requires-Dist: black ; extra == 'dev'
